askpq/__init__.py
askpq-0.3.0.dist-info/licenses/LICENSE
askpq-0.3.0.dist-info/WHEEL
askpq-0.3.0.dist-info/METADATA
askpq-0.3.0.dist-info/RECORD
