Metadata-Version: 2.4
Name: askpq
Version: 0.3.0
Summary: Python client for the Askpq data service.
Author: Abid
Author-email: Abid <41392423+abidsikder@users.noreply.github.com>
License-Expression: MIT
License-File: LICENSE
Classifier: License :: OSI Approved :: MIT License
Classifier: Programming Language :: Python :: 3.11
Classifier: Programming Language :: Python :: 3.12
Classifier: Programming Language :: Python :: 3.13
Classifier: Operating System :: OS Independent
Classifier: Topic :: Scientific/Engineering
Requires-Dist: httpx>=0.28.1
Requires-Dist: icechunk>=1.1.4
Requires-Dist: xarray[io]>=2025.8.0
Requires-Python: >=3.11
Project-URL: Askpq, https://askpq.com
Project-URL: Documentation, https://pypi-askpq.askpq.com
